src/__init__.py
src/main.py
src/pytuist.py
src/render.py
pytuist-0.0.1a3.dist-info/entry_points.txt
pytuist-0.0.1a3.dist-info/LICENSE
pytuist-0.0.1a3.dist-info/METADATA
pytuist-0.0.1a3.dist-info/WHEEL
pytuist-0.0.1a3.dist-info/RECORD
