Metadata-Version: 2.1
Name: pytuist
Version: 0.0.1a3
Summary: A TUI (terminal user interface) for pytest, because testing should be fun.
Author: Nic Harvey
Author-email: nicharvey@protonmail.com
Requires-Python: >=3.10,<4.0
Classifier: Programming Language :: Python :: 3
Classifier: Programming Language :: Python :: 3.10
Classifier: Programming Language :: Python :: 3.11
Requires-Dist: rich (>=13.3.1,<14.0.0)
